cybershell/__init__.py
cybershell/__main__.py
cybershell-0.1.3.dist-info/METADATA
cybershell-0.1.3.dist-info/WHEEL
cybershell-0.1.3.dist-info/entry_points.txt
cybershell-0.1.3.dist-info/licenses/LICENSE
cybershell-0.1.3.dist-info/RECORD
