Metadata-Version: 2.4
Name: cybershell
Version: 0.1.3
Summary: The Shell That Shapes Your Code
Author-email: Hyperoot <rajesh@hyperoot.dev>
License: Copyright © 2025 hyperoot.dev
License-File: LICENSE
Requires-Python: >=3.13
Requires-Dist: bump-my-version>=0.32.2
